dwm1001.py
pydwm1001-0.12.1.dist-info/LICENSE
pydwm1001-0.12.1.dist-info/METADATA
pydwm1001-0.12.1.dist-info/WHEEL
pydwm1001-0.12.1.dist-info/top_level.txt
pydwm1001-0.12.1.dist-info/RECORD
